xagpy/__init__.py
xagpy/api.py
xagpy-0.55.dist-info/LICENSE
xagpy-0.55.dist-info/METADATA
xagpy-0.55.dist-info/WHEEL
xagpy-0.55.dist-info/top_level.txt
xagpy-0.55.dist-info/RECORD
